{
  "schema_version": "1.0",
  "run_ts_utc": "2026-04-27T03:33:45.843590+00:00",
  "branch": "main",
  "anomalies_detected": true,
  "checks": {
    "repo_structure": "pass",
    "config_drift": "pass",
    "governance_contracts_present": "fail",
    "required_artifacts": "fail",
    "no_deprecated_dirs": "pass",
    "no_clawdbot_moltbot": "pass"
  },
  "details": [
    "Missing: reports/board — directory does not exist",
    "required_artifacts: reports/board missing or not a directory"
  ],
  "slack_sent": false,
  "issue_opened": false,
  "issue_note": "gh CLI is read-only; manual GitHub issue creation required for anomalies"
}